{
    "@class": "com.kony.gen.viz.model.component.KVizButton",
    "DNDConfig": null,
    "_height_": {
        "type": "string",
        "value": "50dp"
    },
    "_left_": {
        "type": "string",
        "value": "481dp"
    },
    "_margin_": [
        6,
        6,
        6,
        6
    ],
    "_padding_": [
        0,
        0,
        0,
        0
    ],
    "_skin_": "sfa5e6fa727c428a9be3a507d38b7f56",
    "_text_": "Button",
    "_top_": {
        "type": "string",
        "value": "436dp"
    },
    "_width_": {
        "type": "string",
        "value": "300dp"
    },
    "canUpdateUI": true,
    "containerweight": 100,
    "contentalignment": 5,
    "displaytext": true,
    "focusskin": "sa012444fc5d4593ad77e11e255d2be1",
    "id": "Button0c3de10973f8145",
    "info": null,
    "iscustomlayout": false,
    "isvisible": true,
    "kuid": "fb31d030d0a746a19b30c394ce22ca6a",
    "name": "kony.ui.Button",
    "parent": "Form1",
    "pf": "Form1",
    "retaincontentalignment": false,
    "retainflexpositionproperties": false,
    "wType": "Button",
    "zindex": 1
}